{"Version":"1.0.0.0","LastState":11,"Modules":[{"ModuleName":"Front Left","ModuleId":0,"Encoder":{"Id":13,"Name":"FL-Enc","Model":"CANCoder vers. H","CANbus":"1846C660394C4853202020500C1D18FF","CANbusFriendly":"canivore","SelectedMotorType":null,"IsStandaloneFx":false},"SteerMotor":{"Id":12,"Name":"FL-Steer","Model":"Talon FX","CANbus":"1846C660394C4853202020500C1D18FF","CANbusFriendly":"canivore","SelectedMotorType":{"Name":"WCP Kraken x60","FreeSpeedRps":96.7},"IsStandaloneFx":false},"DriveMotor":{"Id":11,"Name":"FL-Drive","Model":"Talon FX","CANbus":"1846C660394C4853202020500C1D18FF","CANbusFriendly":"canivore","SelectedMotorType":{"Name":"WCP Kraken x60","FreeSpeedRps":96.7},"IsStandaloneFx":false},"IsEncoderInverted":false,"IsSteerInverted":true,"SelectedEncoderType":"CANcoder","EncoderOffset":0.28173828125,"DriveMotorSelectionState":1,"SteerMotorSelectionState":1,"SteerEncoderSelectionState":1,"IsModuleValidationComplete":true,"ValidatedSteerId":12,"ValidatedDriveId":11,"ValidatedEncoderId":13,"AvailEncoders":[{"Id":13,"Name":"FL-Enc","Model":"CANCoder vers. H","CANbus":"1846C660394C4853202020500C1D18FF","CANbusFriendly":"canivore","SelectedMotorType":null,"IsStandaloneFx":false},{"Id":23,"Name":"FR-Enc","Model":"CANCoder vers. H","CANbus":"1846C660394C4853202020500C1D18FF","CANbusFriendly":"canivore","SelectedMotorType":null,"IsStandaloneFx":false},{"Id":33,"Name":"BR-Enc","Model":"CANCoder vers. H","CANbus":"1846C660394C4853202020500C1D18FF","CANbusFriendly":"canivore","SelectedMotorType":null,"IsStandaloneFx":false},{"Id":43,"Name":"BL-Enc","Model":"CANCoder vers. H","CANbus":"1846C660394C4853202020500C1D18FF","CANbusFriendly":"canivore","SelectedMotorType":null,"IsStandaloneFx":false},{"Id":53,"Name":"Shooter Angle Enc","Model":"CANCoder vers. H","CANbus":"rio","CANbusFriendly":"","SelectedMotorType":null,"IsStandaloneFx":false}],"IsEncoderTypeCAN":true,"IsDeviceSelectionCompleted":true,"IsConfigurationCompleted":true,"AvailEncoderTypes":["CANcoder"]},{"ModuleName":"Front Right","ModuleId":1,"Encoder":{"Id":23,"Name":"FR-Enc","Model":"CANCoder vers. H","CANbus":"1846C660394C4853202020500C1D18FF","CANbusFriendly":"canivore","SelectedMotorType":null,"IsStandaloneFx":false},"SteerMotor":{"Id":22,"Name":"FR-Steer","Model":"Talon FX","CANbus":"1846C660394C4853202020500C1D18FF","CANbusFriendly":"canivore","SelectedMotorType":{"Name":"WCP Kraken x60","FreeSpeedRps":96.7},"IsStandaloneFx":false},"DriveMotor":{"Id":21,"Name":"FR-Drive","Model":"Talon FX","CANbus":"1846C660394C4853202020500C1D18FF","CANbusFriendly":"canivore","SelectedMotorType":{"Name":"WCP Kraken x60","FreeSpeedRps":96.7},"IsStandaloneFx":false},"IsEncoderInverted":false,"IsSteerInverted":true,"SelectedEncoderType":"CANcoder","EncoderOffset":-0.21337890625,"DriveMotorSelectionState":1,"SteerMotorSelectionState":1,"SteerEncoderSelectionState":1,"IsModuleValidationComplete":true,"ValidatedSteerId":22,"ValidatedDriveId":21,"ValidatedEncoderId":23,"AvailEncoders":[{"Id":13,"Name":"FL-Enc","Model":"CANCoder vers. H","CANbus":"1846C660394C4853202020500C1D18FF","CANbusFriendly":"canivore","SelectedMotorType":null,"IsStandaloneFx":false},{"Id":23,"Name":"FR-Enc","Model":"CANCoder vers. H","CANbus":"1846C660394C4853202020500C1D18FF","CANbusFriendly":"canivore","SelectedMotorType":null,"IsStandaloneFx":false},{"Id":33,"Name":"BR-Enc","Model":"CANCoder vers. H","CANbus":"1846C660394C4853202020500C1D18FF","CANbusFriendly":"canivore","SelectedMotorType":null,"IsStandaloneFx":false},{"Id":43,"Name":"BL-Enc","Model":"CANCoder vers. H","CANbus":"1846C660394C4853202020500C1D18FF","CANbusFriendly":"canivore","SelectedMotorType":null,"IsStandaloneFx":false},{"Id":53,"Name":"Shooter Angle Enc","Model":"CANCoder vers. H","CANbus":"rio","CANbusFriendly":"","SelectedMotorType":null,"IsStandaloneFx":false}],"IsEncoderTypeCAN":true,"IsDeviceSelectionCompleted":true,"IsConfigurationCompleted":true,"AvailEncoderTypes":["CANcoder"]},{"ModuleName":"Back Left","ModuleId":2,"Encoder":{"Id":43,"Name":"BL-Enc","Model":"CANCoder vers. H","CANbus":"1846C660394C4853202020500C1D18FF","CANbusFriendly":"canivore","SelectedMotorType":null,"IsStandaloneFx":false},"SteerMotor":{"Id":32,"Name":"BL-Steer","Model":"Talon FX","CANbus":"1846C660394C4853202020500C1D18FF","CANbusFriendly":"canivore","SelectedMotorType":{"Name":"WCP Kraken x60","FreeSpeedRps":96.7},"IsStandaloneFx":false},"DriveMotor":{"Id":31,"Name":"BL-Drive","Model":"Talon FX","CANbus":"1846C660394C4853202020500C1D18FF","CANbusFriendly":"canivore","SelectedMotorType":{"Name":"WCP Kraken x60","FreeSpeedRps":96.7},"IsStandaloneFx":false},"IsEncoderInverted":false,"IsSteerInverted":true,"SelectedEncoderType":"CANcoder","EncoderOffset":-0.02880859375,"DriveMotorSelectionState":1,"SteerMotorSelectionState":1,"SteerEncoderSelectionState":1,"IsModuleValidationComplete":true,"ValidatedSteerId":32,"ValidatedDriveId":31,"ValidatedEncoderId":43,"AvailEncoders":[{"Id":13,"Name":"FL-Enc","Model":"CANCoder vers. H","CANbus":"1846C660394C4853202020500C1D18FF","CANbusFriendly":"canivore","SelectedMotorType":null,"IsStandaloneFx":false},{"Id":23,"Name":"FR-Enc","Model":"CANCoder vers. H","CANbus":"1846C660394C4853202020500C1D18FF","CANbusFriendly":"canivore","SelectedMotorType":null,"IsStandaloneFx":false},{"Id":33,"Name":"BR-Enc","Model":"CANCoder vers. H","CANbus":"1846C660394C4853202020500C1D18FF","CANbusFriendly":"canivore","SelectedMotorType":null,"IsStandaloneFx":false},{"Id":43,"Name":"BL-Enc","Model":"CANCoder vers. H","CANbus":"1846C660394C4853202020500C1D18FF","CANbusFriendly":"canivore","SelectedMotorType":null,"IsStandaloneFx":false},{"Id":53,"Name":"Shooter Angle Enc","Model":"CANCoder vers. H","CANbus":"rio","CANbusFriendly":"","SelectedMotorType":null,"IsStandaloneFx":false}],"IsEncoderTypeCAN":true,"IsDeviceSelectionCompleted":true,"IsConfigurationCompleted":true,"AvailEncoderTypes":["CANcoder"]},{"ModuleName":"Back Right","ModuleId":3,"Encoder":{"Id":33,"Name":"BR-Enc","Model":"CANCoder vers. H","CANbus":"1846C660394C4853202020500C1D18FF","CANbusFriendly":"canivore","SelectedMotorType":null,"IsStandaloneFx":false},"SteerMotor":{"Id":42,"Name":"BR-Steer","Model":"Talon FX","CANbus":"1846C660394C4853202020500C1D18FF","CANbusFriendly":"canivore","SelectedMotorType":{"Name":"WCP Kraken x60","FreeSpeedRps":96.7},"IsStandaloneFx":false},"DriveMotor":{"Id":41,"Name":"BR-Drive","Model":"Talon FX","CANbus":"1846C660394C4853202020500C1D18FF","CANbusFriendly":"canivore","SelectedMotorType":{"Name":"WCP Kraken x60","FreeSpeedRps":96.7},"IsStandaloneFx":false},"IsEncoderInverted":false,"IsSteerInverted":true,"SelectedEncoderType":"CANcoder","EncoderOffset":-0.18359375,"DriveMotorSelectionState":1,"SteerMotorSelectionState":1,"SteerEncoderSelectionState":1,"IsModuleValidationComplete":true,"ValidatedSteerId":42,"ValidatedDriveId":41,"ValidatedEncoderId":33,"AvailEncoders":[{"Id":13,"Name":"FL-Enc","Model":"CANCoder vers. H","CANbus":"1846C660394C4853202020500C1D18FF","CANbusFriendly":"canivore","SelectedMotorType":null,"IsStandaloneFx":false},{"Id":23,"Name":"FR-Enc","Model":"CANCoder vers. H","CANbus":"1846C660394C4853202020500C1D18FF","CANbusFriendly":"canivore","SelectedMotorType":null,"IsStandaloneFx":false},{"Id":33,"Name":"BR-Enc","Model":"CANCoder vers. H","CANbus":"1846C660394C4853202020500C1D18FF","CANbusFriendly":"canivore","SelectedMotorType":null,"IsStandaloneFx":false},{"Id":43,"Name":"BL-Enc","Model":"CANCoder vers. H","CANbus":"1846C660394C4853202020500C1D18FF","CANbusFriendly":"canivore","SelectedMotorType":null,"IsStandaloneFx":false},{"Id":53,"Name":"Shooter Angle Enc","Model":"CANCoder vers. H","CANbus":"rio","CANbusFriendly":"","SelectedMotorType":null,"IsStandaloneFx":false}],"IsEncoderTypeCAN":true,"IsDeviceSelectionCompleted":true,"IsConfigurationCompleted":true,"AvailEncoderTypes":["CANcoder"]}],"SwerveOptions":{"kSpeedAt12Volts":9.462920591575315,"Gyro":{"Id":1,"Name":"Pigeon 2","Model":"Pigeon 2 vers. S","CANbus":"1846C660394C4853202020500C1D18FF","CANbusFriendly":"canivore","SelectedMotorType":null,"IsStandaloneFx":false},"IsValidGyroCANbus":true,"VerticalTrackSizeInches":21.0,"HorizontalTrackSizeInches":21.0,"WheelRadiusInches":4.0,"IsLeftSideInverted":false,"IsRightSideInverted":true,"SwerveModuleType":4,"SwerveModuleConfiguration":{"ModuleBrand":4,"DriveRatio":6.746031746031747,"SteerRatio":21.428571428571427,"CouplingRatio":3.5714285714285716,"CustomName":"L2"},"HasVerifiedSteer":true,"HasVerifiedDrive":true,"IsValidConfiguration":true}}